pytest_scim2_server/__init__.py
pytest_scim2_server-0.1.6.dist-info/METADATA
pytest_scim2_server-0.1.6.dist-info/WHEEL
pytest_scim2_server-0.1.6.dist-info/entry_points.txt
pytest_scim2_server-0.1.6.dist-info/licenses/LICENSE
pytest_scim2_server-0.1.6.dist-info/RECORD
