Metadata-Version: 2.4
Name: pytest-scim2-server
Version: 0.1.6
Summary: SCIM2 server fixture for Pytest
Project-URL: repository, https://gitlab.com/pytest-dev/pytest-scim2-server
Author-email: Yaal Coop <contact@yaal.coop>
Maintainer-email: Éloi Rivard <eloi@yaal.coop>
License: MIT License
License-File: LICENSE
Keywords: fixture,pytest,rfc7643,rfc7644,scim,scim2
Classifier: Development Status :: 4 - Beta
Classifier: Intended Audience :: Developers
Classifier: License :: OSI Approved :: MIT License
Classifier: Operating System :: OS Independent
Classifier: Programming Language :: Python
Classifier: Programming Language :: Python :: 3.10
Classifier: Programming Language :: Python :: 3.11
Classifier: Programming Language :: Python :: 3.12
Classifier: Programming Language :: Python :: 3.13
Requires-Python: >=3.10
Requires-Dist: portpicker>=1.6.0
Requires-Dist: pytest>=8.3.4
Requires-Dist: scim2-server>=0.1.4
